kitsune/__init__.py
kitsune/__main__.py
kitsune/colors.py
kitsune/file.py
kitsune/kitsune.py
python_kitsune-0.1.4.dist-info/LICENSE
python_kitsune-0.1.4.dist-info/METADATA
python_kitsune-0.1.4.dist-info/WHEEL
python_kitsune-0.1.4.dist-info/entry_points.txt
python_kitsune-0.1.4.dist-info/top_level.txt
python_kitsune-0.1.4.dist-info/RECORD
